qb_gui_api-1.3.2.dist-info/licenses/LICENSE
quickbooks_gui_api/__init__.py
quickbooks_gui_api/__main__.py
quickbooks_gui_api/config_init.py
quickbooks_gui_api/gui_api.py
quickbooks_gui_api/apis/__init__.py
quickbooks_gui_api/apis/api_exceptions.py
quickbooks_gui_api/apis/invoices.py
quickbooks_gui_api/apis/reports.py
quickbooks_gui_api/managers/__init__.py
quickbooks_gui_api/managers/file.py
quickbooks_gui_api/managers/helper.py
quickbooks_gui_api/managers/image.py
quickbooks_gui_api/managers/manager_exceptions.py
quickbooks_gui_api/managers/ocr.py
quickbooks_gui_api/managers/processes.py
quickbooks_gui_api/managers/string.py
quickbooks_gui_api/managers/window.py
quickbooks_gui_api/models/__init__.py
quickbooks_gui_api/models/element.py
quickbooks_gui_api/models/image.py
quickbooks_gui_api/models/invoice.py
quickbooks_gui_api/models/report.py
quickbooks_gui_api/utilities/__init__.py
quickbooks_gui_api/utilities/logger_factory.py
quickbooks_gui_api/utilities/utilities.py
qb_gui_api-1.3.2.dist-info/METADATA
qb_gui_api-1.3.2.dist-info/WHEEL
qb_gui_api-1.3.2.dist-info/entry_points.txt
qb_gui_api-1.3.2.dist-info/top_level.txt
qb_gui_api-1.3.2.dist-info/RECORD
