Metadata-Version: 2.4
Name: qb-gui-api
Version: 1.3.2
Summary: A Python toolkit for automating QuickBooks Desktop via the GUI
Author-email: Derek Banker <dbb2002@gmail.com>
License-Expression: Apache-2.0
Keywords: quickbooks,quickbooks desktop,quickbooks enterprise,invoice,reports
Classifier: Programming Language :: Python :: 3
Classifier: Operating System :: Microsoft :: Windows
Requires-Python: >=3.10
License-File: LICENSE
Requires-Dist: psutil>=7.0.0
Requires-Dist: toml_init>=0.1.1
Requires-Dist: pytomlpp>=1.0
Requires-Dist: python-dotenv>=0.19
Requires-Dist: pywinauto>=0.6
Requires-Dist: pyautogui>=0.9
Requires-Dist: pywin32>=306; platform_system == "Windows"
Requires-Dist: numpy>=1.21
Requires-Dist: opencv-python>=4.5
Requires-Dist: pytesseract>=0.3
Requires-Dist: mss>=9.0
Requires-Dist: Pillow>=9.0
Requires-Dist: rapidfuzz>=3.13.0
Requires-Dist: click>=8.0
Dynamic: license-file
